__init__.py
glassInit.py
glassinit-0.0.6.dist-info/licenses/LICENSE
glassinit-0.0.6.dist-info/METADATA
glassinit-0.0.6.dist-info/WHEEL
glassinit-0.0.6.dist-info/top_level.txt
glassinit-0.0.6.dist-info/RECORD
