Metadata-Version: 2.4
Name: glassInit
Version: 0.0.6
Summary: glassInit is a way to initialize the parameters of a neural network layer @pytorch. It is suitable for shortcut connections where tensor sizes need to be adjusted. The flow of information between forward and backward propagation is maximized while adjusting the tensor size. 
Author-email: Psyche Halo <Psyche@WinsGod.com>
Project-URL: Homepage, https://github.com/PsycheHalo/glassInit
Project-URL: Issues, https://github.com/PsycheHalo/glassInit/issues
Keywords: glassInit,initialize,shortcut,PyTorch,AI,neural,NN,connections,Skip Connections,Res
Classifier: Programming Language :: Python :: 3
Classifier: Operating System :: OS Independent
Requires-Python: >=3.8
License-File: LICENSE
Requires-Dist: torch>=1.7.0
Dynamic: license-file
